simpleline/__init__.py
simpleline/errors.py
simpleline/global_configuration.py
simpleline/logging.py
simpleline/event_loop/__init__.py
simpleline/event_loop/event_queue.py
simpleline/event_loop/glib_event_loop.py
simpleline/event_loop/main_loop.py
simpleline/event_loop/signals.py
simpleline/event_loop/ticket_machine.py
simpleline/input/__init__.py
simpleline/input/input_handler.py
simpleline/input/input_threading.py
simpleline/render/__init__.py
simpleline/render/adv_widgets.py
simpleline/render/containers.py
simpleline/render/prompt.py
simpleline/render/screen_handler.py
simpleline/render/screen_scheduler.py
simpleline/render/screen_stack.py
simpleline/render/widgets.py
simpleline/render/screen/__init__.py
simpleline/render/screen/input_manager.py
simpleline/render/screen/signal_handler.py
simpleline/utils/__init__.py
simpleline/utils/i18n.py
simpleline-1.9.0.dist-info/LICENSE.md
simpleline-1.9.0.dist-info/METADATA
simpleline-1.9.0.dist-info/WHEEL
simpleline-1.9.0.dist-info/top_level.txt
simpleline-1.9.0.dist-info/RECORD
