Metadata-Version: 2.1
Name: simpleline
Version: 1.9.0
Summary: Python text UI framework
Home-page: https://github.com/rhinstaller/python-simpleline
Author: Jiri Konecny
Author-email: jkonecny@redhat.com
License: UNKNOWN
Keywords: ui text library glib
Platform: UNKNOWN
Classifier: Development Status :: 5 - Production/Stable
Classifier: Intended Audience :: Developers
Classifier: Topic :: Software Development :: User Interfaces
Classifier: License :: OSI Approved :: GNU Lesser General Public License v3 or later (LGPLv3+)
Classifier: Programming Language :: Python :: 3
Requires-Python: >=3.4
